LICENSE.txt
README.rst
setup.py
binmap/__init__.py
binmap/st.py
binmap/types.py
binmap.egg-info/PKG-INFO
binmap.egg-info/SOURCES.txt
binmap.egg-info/dependency_links.txt
binmap.egg-info/top_level.txt
tests/__init__.py
tests/test_binmap.py