Metadata-Version: 2.1
Name: binmap
Version: 1.2.1
Summary: A base class for creating binary parsing and packing classes
Home-page: https://github.com/HeMan/binmap
Author: Jimmy Hedman
Author-email: jimmy.hedman@gmail.com
Classifier: Development Status :: 5 - Production/Stable
Classifier: Programming Language :: Python :: 3
Classifier: Programming Language :: Python :: 3.8
Classifier: Programming Language :: Python :: 3.9
Classifier: Programming Language :: Python :: 3.10
Classifier: Programming Language :: Python :: 3.11
Classifier: Programming Language :: Python :: 3.12
Classifier: Programming Language :: Python :: 3.13
License-File: LICENSE.txt
